sc2_simulator.cp38-win_amd64.pyd
sc2_simulator-0.0.3.dist-info/METADATA
sc2_simulator-0.0.3.dist-info/WHEEL
sc2_simulator-0.0.3.dist-info/top_level.txt
sc2_simulator-0.0.3.dist-info/RECORD
