Metadata-Version: 2.1
Name: sc2-simulator
Version: 0.0.3
Summary: Python bindings for sc2-libvoxelbot
Home-page: UNKNOWN
Author: Luke Holroyd
Author-email: lukejholroyd@gmail.com
License: UNKNOWN
Platform: UNKNOWN
